LICENSE
MANIFEST.in
README.rst
requirements-docs.txt
requirements-test.txt
requirements.txt
setup.cfg
setup.py
tox.ini
usage.txt
docs/Makefile
docs/api.rst
docs/conf.py
docs/index.rst
docs/make.bat
docs/modules.rst
docs/txt2contincd.rst
src/txt2contincd/__init__.py
src/txt2contincd/args.py
src/txt2contincd/conf.py
src/txt2contincd/config.spec
src/txt2contincd/console.py
src/txt2contincd/main.py
src/txt2contincd/utils.py
src/txt2contincd.egg-info/PKG-INFO
src/txt2contincd.egg-info/SOURCES.txt
src/txt2contincd.egg-info/dependency_links.txt
src/txt2contincd.egg-info/entry_points.txt
src/txt2contincd.egg-info/requires.txt
src/txt2contincd.egg-info/top_level.txt
src/txt2contincd.egg-info/zip-safe
tests/__init__.py
tests/test_args.py
tests/test_conf.py