Metadata-Version: 1.1
Name: txt2contincd
Version: 0.1.0
Summary: Convert raw text data files into a CONTIN-CD input file.
Home-page: https://github.com/lambdalisue/txt2contincd
Author: Alisue
Author-email: lambdalisue@hashnote.net
License: MIT
Download-URL: https://github.com/lambdalisue/txt2contincd/tarball/master
Keywords: raw text data convert CONTINT
Platform: UNKNOWN
Classifier: Development Status :: 3 - Alpha
Classifier: Intended Audience :: Developers
Classifier: License :: OSI Approved :: MIT License
Classifier: Programming Language :: Python
Classifier: Programming Language :: Python :: 2.6
Classifier: Programming Language :: Python :: 2.7
